odoo/addons/stock_picking_report_summary/README.rst
odoo/addons/stock_picking_report_summary/__init__.py
odoo/addons/stock_picking_report_summary/__manifest__.py
odoo/addons/stock_picking_report_summary/i18n/fr.po
odoo/addons/stock_picking_report_summary/i18n/it.po
odoo/addons/stock_picking_report_summary/i18n/stock_picking_report_summary.pot
odoo/addons/stock_picking_report_summary/readme/CONTRIBUTORS.rst
odoo/addons/stock_picking_report_summary/readme/DESCRIPTION.rst
odoo/addons/stock_picking_report_summary/readme/USAGE.rst
odoo/addons/stock_picking_report_summary/reports/report_print_picking_summary.xml
odoo/addons/stock_picking_report_summary/reports/report_print_picking_summary_template.xml
odoo/addons/stock_picking_report_summary/security/ir.model.access.csv
odoo/addons/stock_picking_report_summary/static/description/icon.png
odoo/addons/stock_picking_report_summary/static/description/index.html
odoo/addons/stock_picking_report_summary/static/description/new_print_action.png
odoo/addons/stock_picking_report_summary/static/description/pdf_report.png
odoo/addons/stock_picking_report_summary/static/description/wizard.png
odoo/addons/stock_picking_report_summary/tests/__init__.py
odoo/addons/stock_picking_report_summary/tests/test_module.py
odoo/addons/stock_picking_report_summary/wizards/__init__.py
odoo/addons/stock_picking_report_summary/wizards/picking_summary_wizard.py
odoo/addons/stock_picking_report_summary/wizards/picking_summary_wizard_picking.py
odoo/addons/stock_picking_report_summary/wizards/picking_summary_wizard_product.py
odoo/addons/stock_picking_report_summary/wizards/view_picking_summary_wizard.xml
odoo_addon_stock_picking_report_summary-16.0.1.0.0.4.dist-info/METADATA
odoo_addon_stock_picking_report_summary-16.0.1.0.0.4.dist-info/WHEEL
odoo_addon_stock_picking_report_summary-16.0.1.0.0.4.dist-info/top_level.txt
odoo_addon_stock_picking_report_summary-16.0.1.0.0.4.dist-info/RECORD
